atlasman/__init__.py
atlasman/__main__.py
atlasman/config.py
atlasman/jira_commands.py
atlasman/trello_commands.py
atlasman/constants/__init__.py
atlasman/constants/jira_field_types.py
atlas_man-0.2.1.dist-info/LICENSE
atlas_man-0.2.1.dist-info/METADATA
atlas_man-0.2.1.dist-info/WHEEL
atlas_man-0.2.1.dist-info/entry_points.txt
atlas_man-0.2.1.dist-info/top_level.txt
atlas_man-0.2.1.dist-info/RECORD
