Metadata-Version: 2.1
Name: atlas-man
Version: 0.2.1
Summary: A CLI tool for managing Trello and Jira
Home-page: https://github.com/tylerjwoodfin/atlas-man
Author: Tyler Woodfin
Author-email: feedback-atlas-man@tyler.cloud
Project-URL: Bug Tracker, https://github.com/tylerjwoodfin/atlas-man/issues
Classifier: Programming Language :: Python :: 3
Classifier: Programming Language :: Python :: 3.6
Classifier: Programming Language :: Python :: 3.7
Classifier: Programming Language :: Python :: 3.8
Classifier: Programming Language :: Python :: 3.9
Classifier: License :: OSI Approved :: MIT License
Classifier: Operating System :: OS Independent
Requires-Python: >=3.6
License-File: LICENSE
Requires-Dist: cabinet
Requires-Dist: python_dateutil
Requires-Dist: pytz
Requires-Dist: requests
Requires-Dist: prompt_toolkit
Requires-Dist: py-trello
Requires-Dist: jira
Requires-Dist: tabulate
